MondayShareableLinks/DisableShareLinks.py
MondayShareableLinks/__init__.py
MondayShareableLinks-2.0.0.dist-info/METADATA
MondayShareableLinks-2.0.0.dist-info/WHEEL
MondayShareableLinks-2.0.0.dist-info/entry_points.txt
MondayShareableLinks-2.0.0.dist-info/top_level.txt
MondayShareableLinks-2.0.0.dist-info/RECORD
